<mvc:View controllerName="ns.businesspartners.controller.Suppliers"
    xmlns:mvc="sap.ui.core.mvc" displayBlock="true"
    xmlns="sap.m">
    <Page id="page" title="{i18n>title}">
        <content>
            <List noDataText="Drop list item here" id="list0" items="{/BusinessPartnerSet}">
                <items>
                    <StandardListItem type="Navigation" title="{CompanyName}" description="Description text{WebAddress}" icon="sap-icon://picture" id="item0" />
                </items>
            </List>
        </content>
    </Page>
</mvc:View>
